divik/__init__.py
divik/_cli/__init__.py
divik/_cli/fit_clusters.gin
divik/_cli/fit_clusters.py
divik/_matlab_legacy.py
divik/_summary.py
divik/cluster/__init__.py
divik/cluster/_divik/__init__.py
divik/cluster/_divik/_backend.py
divik/cluster/_divik/_report.py
divik/cluster/_divik/_sklearn.py
divik/cluster/_kmeans/__init__.py
divik/cluster/_kmeans/_core.py
divik/cluster/_kmeans/_dunn.py
divik/cluster/_kmeans/_gap.py
divik/cluster/_kmeans/_initialization.py
divik/cluster/_two_step.py
divik/core/__init__.py
divik/core/_cache.py
divik/core/_gin_compat.py
divik/core/_parallel.py
divik/core/_seed.py
divik/core/_subsets.py
divik/core/_types.py
divik/core/_utils.py
divik/core/gin_sklearn_configurables.py
divik/core/io/__init__.py
divik/core/io/_data_io.py
divik/core/io/_model_io.py
divik/feature_extraction/__init__.py
divik/feature_extraction/_histogram.py
divik/feature_extraction/_pca.py
divik/feature_extraction/_spectral.py
divik/feature_selection/__init__.py
divik/feature_selection/_exims/__init__.py
divik/feature_selection/_exims/_exims.py
divik/feature_selection/_exims/_matlab_alike.py
divik/feature_selection/_exims/_selection.py
divik/feature_selection/_exims/_sklearn.py
divik/feature_selection/_exims/_structness.py
divik/feature_selection/_gmm_selector.py
divik/feature_selection/_outlier.py
divik/feature_selection/_percentage_selector.py
divik/feature_selection/_specialized.py
divik/feature_selection/_stat_selector_mixin.py
divik/sampler/__init__.py
divik/sampler/_core.py
divik/sampler/_stratified_sampler.py
divik/sampler/_uniform_sampler.py
divik/score/__init__.py
divik/score/_dunn.py
divik/score/_gap.py
divik/score/_sampled_gap.py
gamred_native.cp39-win_amd64.pyd
divik-3.2.4.dist-info/entry_points.txt
divik-3.2.4.dist-info/LICENSE
divik-3.2.4.dist-info/METADATA
divik-3.2.4.dist-info/WHEEL
divik-3.2.4.dist-info/RECORD
