Metadata-Version: 2.1
Name: divik
Version: 3.2.4
Summary: Divisive iK-means algorithm implementation
Home-page: https://github.com/gmrukwa/divik
License: Apache-2.0
Author: Grzegorz Mrukwa
Author-email: g.mrukwa@gmail.com
Requires-Python: >=3.7.1,<4.0
Classifier: Development Status :: 5 - Production/Stable
Classifier: Intended Audience :: Developers
Classifier: Intended Audience :: Science/Research
Classifier: License :: OSI Approved :: Apache Software License
Classifier: Programming Language :: Python :: 3
Classifier: Programming Language :: Python :: 3.8
Classifier: Programming Language :: Python :: 3.9
Classifier: Programming Language :: Python :: 3.10
Classifier: Programming Language :: Python :: 3.11
Classifier: Programming Language :: Python :: 3.12
Classifier: Programming Language :: Python :: 3.7
Classifier: Topic :: Scientific/Engineering :: Artificial Intelligence
Classifier: Topic :: Scientific/Engineering :: Bio-Informatics
Classifier: Topic :: Scientific/Engineering :: Information Analysis
Classifier: Topic :: Scientific/Engineering :: Medical Science Apps.
Provides-Extra: all
Provides-Extra: gin
Provides-Extra: polyaxon
Requires-Dist: dask-distance (>=0.2.0,<0.3.0)
Requires-Dist: dask[dataframe] (>=2.14.0)
Requires-Dist: gin-config (>=0.5.0,<0.6.0) ; extra == "gin" or extra == "all"
Requires-Dist: h5py (>=2.8.0)
Requires-Dist: importlib-metadata (>=6.0,<7.0) ; python_version < "3.8"
Requires-Dist: joblib (>=1.0.0,<2.0.0)
Requires-Dist: kneed (>=0.5.1)
Requires-Dist: matplotlib (>=3.3.3,<4.0.0)
Requires-Dist: numpy (>=0.12.1)
Requires-Dist: pandas (>=0.20.3)
Requires-Dist: polyaxon (>=1.5.0,<2.0.0) ; extra == "polyaxon" or extra == "all"
Requires-Dist: scikit-image (>=0.14.1)
Requires-Dist: scikit-learn (>=0.19.0)
Requires-Dist: scipy (>=0.19.1)
Requires-Dist: tqdm (>=4.11.2)
Project-URL: Documentation, https://divik.readthedocs.io/
Project-URL: Repository, https://github.com/gmrukwa/divik
